{
  "active_users": [
    {
      "device_id": "android-588746966-1774507012518",
      "platform": "android",
      "device_type": "android-mobile",
      "session_start": "2026-04-03T11:00:49.739144",
      "last_activity": "2026-04-03T11:05:45.047860",
      "is_active": true,
      "app_version": "1.0.0",
      "status": "online"
    },
    {
      "device_id": "android-588746966-1774922807894",
      "last_activity": "2026-04-03T11:04:25.688895",
      "is_active": true,
      "status": "online",
      "session_start": "2026-04-03T11:02:56.327091",
      "platform": "android",
      "device_type": "android-mobile",
      "app_version": "1.0.0"
    }
  ],
  "last_updated": "2026-04-03T11:05:45.630784",
  "total_active": 2
}