{
  "active_users": [
    {
      "device_id": "android-588746966-1774500898462",
      "platform": "android",
      "device_type": "android-mobile",
      "session_start": "2026-03-26T14:07:42.568480",
      "last_activity": "2026-03-26T14:10:18.293772",
      "is_active": true,
      "app_version": "1.0.0",
      "status": "online"
    },
    {
      "device_id": "windows-629659540-1774372414313",
      "platform": "windows",
      "device_type": "windows-desktop",
      "session_start": "2026-03-26T14:09:06.009483",
      "last_activity": "2026-03-26T14:10:36.523568",
      "is_active": true,
      "app_version": "1.0.0",
      "status": "online"
    }
  ],
  "last_updated": "2026-03-26T14:10:40.135453",
  "total_active": 2
}