{
  "active_users": [
    {
      "device_id": "windows-629659540-1774952896512",
      "last_activity": "2026-04-10T23:34:18.418347",
      "is_active": true,
      "status": "online",
      "session_start": "2026-04-10T23:29:45.410129",
      "platform": "windows",
      "device_type": "windows-desktop",
      "app_version": "1.0.0"
    },
    {
      "device_id": "windows-629659540-1775834874826",
      "last_activity": "2026-04-10T22:35:30.651497",
      "is_active": true,
      "status": "online",
      "session_start": "2026-04-10T22:34:01.222603",
      "platform": "windows",
      "device_type": "windows-desktop",
      "app_version": "1.0.0"
    }
  ],
  "last_updated": "2026-04-10T23:34:22.075859",
  "total_active": 2
}