{
  "active_users": [
    {
      "device_id": "windows-629659540-1775576176769",
      "platform": "windows",
      "device_type": "windows-desktop",
      "session_start": "2026-04-07T23:36:17.073747",
      "last_activity": "2026-04-07T23:38:39.422871",
      "is_active": true,
      "app_version": "1.0.0",
      "status": "online"
    },
    {
      "device_id": "android-588746966-1775571753454",
      "platform": "android",
      "device_type": "android-mobile",
      "session_start": "2026-04-08T01:03:38.300123",
      "last_activity": "2026-04-08T01:04:22.412016",
      "is_active": true,
      "app_version": "1.0.0",
      "status": "online"
    }
  ],
  "last_updated": "2026-04-08T01:04:23.096198",
  "total_active": 2
}