{"latest_version":"4.0.3","update_required":true,"update_message":"Anda menggunakan versi Lama Roby Gaming Launcher!","download_url":"https://www.mediafire.com/folder/d206tmevgyujz/Roby+Gaming+Launcher","release_notes":"Versi 4.0.3 dengan fitur: \nPenambahan\n- Tema Pink\n\nPerbaikan\n- Sistem Views Sudah Diperbaiki\n- Tema Sekarang Sudah Bisa Digunakan\n- Font Sekarang Sudah Bisa Digunakan\n- Sistem Online User Secara Realtime\n\nSilahkan Klik Update Sekarang, Download Dan Pilih Sesuai Platform Yang Kalian Gunakan.","button_text":"Update Sekarang","force_update":true,"last_updated":"2026-03-31T00:00:00.0"}